{
  "cod-missao": "infiltration",
  "versao": 3,
  "edificio": ["Entrada", "Corredor B", "Sala de Servidores", "Laboratório", "Escada 1", "Sala de Reunião", "Escada 2", "Armazém", "Escada 3", "Heliporto"],
  "ligacoes": [
    ["Entrada", "Corredor B"],
    ["Corredor B", "Sala de Servidores"],
    ["Corredor B", "Laboratório"],
    ["Laboratório", "Escada 1"],
    ["Sala de Servidores", "Escada 1"],
    ["Escada 1", "Sala de Reunião"],
    ["Sala de Reunião", "Escada 2"],
    ["Escada 2", "Armazém"],
    ["Armazém", "Escada 3"],
    ["Escada 3", "Heliporto"]
  ],
  "inimigos": [
    {"nome": "enemy1", "poder": 15, "divisao": "Sala de Servidores"},
    {"nome": "enemy2", "poder": 25, "divisao": "Laboratório"},
    {"nome": "enemy3", "poder": 35, "divisao": "Armazém"}
  ],
  "entradas-saidas": ["Entrada", "Heliporto"],
  "alvo": {"divisao": "Sala de Reunião", "tipo": "documentos"},
  "itens": [
    {"divisao": "Laboratório", "pontos-recuperados": 20, "tipo": "kit de vida"},
    {"divisao": "Armazém", "pontos-extra": 40, "tipo": "colete"}
  ]
}